Workbook

Sheet Assumptions
A1: 1. Assumptions — Bear / Base / Bull 가정표
A2: 기업명·분석 기준일: [입력]
A3: 항목 | B3: Bear | C3: Base | D3: Bull
A4: 매출 5Y CAGR (%) | B4: -2 | C4: 8 | D4: 18
A5: 영업이익률 FY5 (%) | B5: 8 | C5: 14 | D5: 18
A6: 적용 PER (배) | B6: 12 | C6: 18 | D6: 24
A7: 적용 EV/EBITDA (배) | B7: 6 | C7: 9 | D7: 12
A8: 적용 PBR (배) | B8: 1 | C8: 1.5 | D8: 2.2
A9: WACC (%) | B9: 9 | C9: 8 | D9: 7
A10: Terminal Growth (%) | B10: 1 | C10: 2 | D10: 3

Sheet IS
A1: 2. IS — 5개년 손익계산서 (단위: 십억원)
A3: 항목 | B3: FY1 | C3: FY2 | D3: FY3E | E3: FY4E | F3: FY5E | G3: 비고
A4: 매출액
A5: 매출원가
A6: 매출총이익 | B6: =B4-B5 -> 0 | C6: =C4-C5 -> 0 | D6: =D4-D5 -> 0 | E6: =E4-E5 -> 0 | F6: =F4-F5 -> 0 | G6: (자동 계산)
A7: 매출총이익률 (%) | B7: =IFERROR(B6/B4*100,0) -> 0 | C7: =IFERROR(C6/C4*100,0) -> 0 | D7: =IFERROR(D6/D4*100,0) -> 0 | E7: =IFERROR(E6/E4*100,0) -> 0 | F7: =IFERROR(F6/F4*100,0) -> 0 | G7: (자동 계산)
A8: 판관비
A9: 영업이익 | B9: =B6-B8 -> 0 | C9: =C6-C8 -> 0 | D9: =D6-D8 -> 0 | E9: =E6-E8 -> 0 | F9: =F6-F8 -> 0 | G9: (자동 계산)
A10: 영업이익률 (%) | B10: =IFERROR(B9/B4*100,0) -> 0 | C10: =IFERROR(C9/C4*100,0) -> 0 | D10: =IFERROR(D9/D4*100,0) -> 0 | E10: =IFERROR(E9/E4*100,0) -> 0 | F10: =IFERROR(F9/F4*100,0) -> 0 | G10: (자동 계산)
A11: 당기순이익
A12: 순이익률 (%) | B12: =IFERROR(B11/B4*100,0) -> 0 | C12: =IFERROR(C11/C4*100,0) -> 0 | D12: =IFERROR(D11/D4*100,0) -> 0 | E12: =IFERROR(E11/E4*100,0) -> 0 | F12: =IFERROR(F11/F4*100,0) -> 0 | G12: (자동 계산)
A13: 매출 YoY (%) | C13: =IFERROR((C4/B4-1)*100,0) -> 0 | D13: =IFERROR((D4/C4-1)*100,0) -> 0 | E13: =IFERROR((E4/D4-1)*100,0) -> 0 | F13: =IFERROR((F4/E4-1)*100,0) -> 0 | G13: (자동 계산)

Sheet BS
A1: 3. BS — 5개년 재무상태표 (단위: 십억원)
A3: 항목 | B3: FY1 | C3: FY2 | D3: FY3E | E3: FY4E | F3: FY5E | G3: Balance Check
A4: 자산총계
A5: 부채총계
A6: 자본총계
A7: 현금성자산
A8: 차입금
A9: Balance Check | B9: =IF(B4=B5+B6,"OK","ERROR") -> OK | C9: =IF(C4=C5+C6,"OK","ERROR") -> OK | D9: =IF(D4=D5+D6,"OK","ERROR") -> OK | E9: =IF(E4=E5+E6,"OK","ERROR") -> OK | F9: =IF(F4=F5+F6,"OK","ERROR") -> OK
A10: 순차입금 (= 차입금 - 현금성자산) | B10: =B8-B7 -> 0 | C10: =C8-C7 -> 0 | D10: =D8-D7 -> 0 | E10: =E8-E7 -> 0 | F10: =F8-F7 -> 0

Sheet CF
A1: 4. CF — 5개년 현금흐름표 (단위: 십억원)
A3: 항목 | B3: FY1 | C3: FY2 | D3: FY3E | E3: FY4E | F3: FY5E | G3: 비고
A4: 영업CF
A5: 투자CF
A6: 재무CF
A7: CAPEX
A8: FCF (= 영업CF - CAPEX) | B8: =B4-B7 -> 0 | C8: =C4-C7 -> 0 | D8: =D4-D7 -> 0 | E8: =E4-E7 -> 0 | F8: =F4-F7 -> 0
A9: CAPEX / 매출 (%) | B9: =IFERROR(B7/IS!B4*100,0) -> 0 | C9: =IFERROR(C7/IS!C4*100,0) -> 0 | D9: =IFERROR(D7/IS!D4*100,0) -> 0 | E9: =IFERROR(E7/IS!E4*100,0) -> 0 | F9: =IFERROR(F7/IS!F4*100,0) -> 0

Sheet Valuation
A1: 5. Valuation — 4종 밸류에이션 (단위: 원)
A3: 방법론 | B3: Bear | C3: Base | D3: Bull | E3: 가중 평균 | F3: 비고
A4: PER 적용 | E4: =AVERAGE(B4:D4) -> #DIV/0! | F4: FY5 EPS × 적용 PER
A5: EV/EBITDA 적용 | E5: =AVERAGE(B5:D5) -> #DIV/0! | F5: (EBITDA × 멀티플 - 순차입금) / 주식수
A6: PBR 적용 | E6: =AVERAGE(B6:D6) -> #DIV/0! | F6: BPS × 적용 PBR
A7: DCF (선택) | E7: =AVERAGE(B7:D7) -> #DIV/0! | F7: 5개년 FCF 할인 + TV
A8: 최종 목표주가 | E8: =AVERAGE(B8:D8) -> #DIV/0! | F8: =AVERAGE(B7:D7) -> #DIV/0!

Sheet Scenario
A1: 6. Scenario — EPS × PER 매트릭스
A3: EPS \ PER | B3: PER 16x | C3: PER 18x | D3: PER 20x | E3: PER 22x | F3: PER 24x
A4: EPS Bear | B4: =$B$4*16 | C4: =$B$4*18 | D4: =$B$4*20 | E4: =$B$4*22 | F4: =$B$4*24
A5: EPS Base | B5: =$B$5*16 | C5: =$B$5*18 | D5: =$B$5*20 | E5: =$B$5*22 | F5: =$B$5*24
A6: EPS Bull | B6: =$B$6*16 | C6: =$B$6*18 | D6: =$B$6*20 | E6: =$B$6*22 | F6: =$B$6*24

Sheet Sensitivity
A1: 7. Sensitivity — 매출 ±15% × OPM ±2%p 민감도
A3: 매출 \ OPM | B3: -2%p | C3: -1%p | D3: Base | E3: +1%p | F3: +2%p
A4: -15%
A5: -7.5%
A6: Base
A7: +7.5%
A8: +15%

Sheet Summary
A1: 8. Summary — 1페이지 요약 (다른 시트 참조)
A3: 종목명·종목코드
A4: 분석 기준일
A5: 투자의견
A6: 목표주가 (가중) | B6: =Valuation!E8 -> #DIV/0!
A7: 현재가
A8: 상승여력 (%) | B8: =IFERROR((B6-B7)/B7*100,0) -> 0
A9: FY1 매출 (십억원) | B9: =IS!B4 -> 0
A10: FY1 영업이익 | B10: =IS!B9 -> 0
A11: FY1 순이익 | B11: =IS!B11 -> 0
A12: FY1 ROE (%)
A13: Balance Check (FY1) | B13: =BS!B9 -> OK
